{"skeleton":{"hash":"vjvijgkQMeg","spine":"4.1.24","x":-948.2,"y":230.77,"width":3870.25,"height":240,"images":"./images/","audio":"E:/팀프로젝트/2023/ui/보스출현/스파인으로"},"bones":[{"name":"root"},{"name":"bone9","parent":"root","x":1009.55,"y":355.65},{"name":"bone","parent":"bone9","length":1939.62,"rotation":-179.81,"x":-20.86,"y":-1.99},{"name":"bone2","parent":"root","x":33.98,"y":454.56},{"name":"bone3","parent":"root","x":457.75,"y":282.28},{"name":"bone4","parent":"root","x":-726.92,"y":324.04},{"name":"bone5","parent":"root","x":-621.71,"y":323.11},{"name":"bone6","parent":"root","x":-513.74,"y":326.81},{"name":"bone7","parent":"root","x":-404.84,"y":318.5},{"name":"bone8","parent":"root","length":369.95,"rotation":-0.13,"x":-269.33,"y":341.7},{"name":"bone10","parent":"root","x":1993.23,"y":454.56}],"slots":[{"name":"Ingame_warning_BG","bone":"bone","attachment":"Ingame_warning_BG"},{"name":"Ingame_warning_BGtop","bone":"bone","attachment":"Ingame_warning_BGtop"},{"name":"Ingame_warning_warning!","bone":"bone2","attachment":"Ingame_warning_warning!"},{"name":"Ingame_warning_warning!3","bone":"bone10","attachment":"Ingame_warning_warning!"},{"name":"Ingame_warning_warning!2","bone":"bone2","attachment":"Ingame_warning_warning!"},{"name":"Ingame_warning_warning!4","bone":"bone10","attachment":"Ingame_warning_warning!"},{"name":"Ingame_warning_Boss","bone":"bone3","attachment":"Ingame_warning_Boss"},{"name":"보","bone":"bone4","attachment":"보"},{"name":"스","bone":"bone5","attachment":"스"},{"name":"출","bone":"bone6","attachment":"출"},{"name":"현","bone":"bone7","attachment":"현"},{"name":"Ingame_warning_Bossname","bone":"bone8","attachment":"Ingame_warning_Bossname"},{"name":"Ingame_warning","bone":"bone2"}],"skins":[{"name":"default","attachments":{"Ingame_warning":{"Ingame_warning":{"x":-374.18,"y":-99.29,"width":892,"height":111}},"Ingame_warning_BG":{"Ingame_warning_BG":{"x":975.9,"y":-0.34,"rotation":179.81,"width":1922,"height":240}},"Ingame_warning_BGtop":{"Ingame_warning_BGtop":{"x":975.9,"y":-0.34,"rotation":179.81,"width":1922,"height":154}},"Ingame_warning_Boss":{"Ingame_warning_Boss":{"x":43.05,"y":68.49,"width":714,"height":240},"Ingame_warning_Boss_2":{"x":70.71,"y":68.12,"width":522,"height":240},"Ingame_warning_Boss_3":{"x":92.22,"y":68.81,"width":768,"height":240}},"Ingame_warning_Bossname":{"Ingame_warning_Bossname":{"x":185.6,"y":12.49,"rotation":0.13,"width":379,"height":74},"Ingame_warning_Bossname_2":{"x":251.42,"y":12.63,"rotation":0.13,"width":538,"height":74},"Ingame_warning_Bossname_3":{"x":185.6,"y":12.49,"rotation":0.13,"width":383,"height":75}},"Ingame_warning_warning!":{"Ingame_warning_warning!":{"x":-21.18,"y":-9.29,"width":1900,"height":35}},"Ingame_warning_warning!2":{"Ingame_warning_warning!":{"x":-21.18,"y":-201.8,"width":1900,"height":35}},"Ingame_warning_warning!3":{"Ingame_warning_warning!":{"x":-21.18,"y":-9.29,"width":1900,"height":35}},"Ingame_warning_warning!4":{"Ingame_warning_warning!":{"x":-21.18,"y":-201.8,"width":1900,"height":35}},"보":{"보":{"x":9.21,"y":34.24,"width":135,"height":93}},"스":{"스":{"x":8.01,"y":35.66,"width":125,"height":94}},"출":{"출":{"x":15.03,"y":28.47,"width":131,"height":111}},"현":{"현":{"x":22.64,"y":38.27,"width":128,"height":110}}}}],"animations":{"Boss appears1":{"slots":{"Ingame_warning_Boss":{"rgba":[{"time":0.9333,"color":"00000000","curve":[0.989,0,1.044,0,0.989,0,1.044,0,0.989,0,1.044,0,0.989,0.33,1.044,1]},{"time":1.1,"color":"000000ff","curve":"stepped"},{"time":1.6667,"color":"000000ff","curve":[1.891,0,1.845,1,1.891,0,1.845,1,1.891,0,1.845,1,1.767,1,1.92,1]},{"time":2,"color":"ffffffff"}],"attachment":[{},{"time":0.9333,"name":"Ingame_warning_Boss"}]},"Ingame_warning_Bossname":{"rgba":[{"time":1.5,"color":"ffffff00","curve":[1.644,1,1.789,1,1.644,1,1.789,1,1.644,1,1.789,1,1.933,0,1.649,1]},{"time":1.9333,"color":"ffffffff"}],"attachment":[{},{"time":1.5667,"name":"Ingame_warning_Bossname"}]},"Ingame_warning_warning!":{"attachment":[{"time":2.6667},{"time":2.7333,"name":"Ingame_warning_warning!"}]},"Ingame_warning_warning!2":{"attachment":[{"time":2.6667},{"time":2.7333,"name":"Ingame_warning_warning!"}]},"Ingame_warning_warning!3":{"attachment":[{},{"time":1.3333,"name":"Ingame_warning_warning!"}]},"Ingame_warning_warning!4":{"attachment":[{},{"time":1.3333,"name":"Ingame_warning_warning!"}]},"보":{"attachment":[{},{"time":0.3333,"name":"보"}]},"스":{"attachment":[{},{"time":0.5333,"name":"스"}]},"출":{"attachment":[{},{"time":0.7333,"name":"출"}]},"현":{"attachment":[{},{"time":0.9333,"name":"현"}]}},"bones":{"bone":{"scale":[{"x":0},{"time":0.3}]},"bone2":{"translate":[{"x":1950.23},{"time":2.6667,"x":-1845.9},{"time":2.7,"x":2259.71},{"time":2.7333,"x":1972.99},{"time":3.1333,"x":1409.31}]},"bone4":{"scale":[{"curve":[0.111,1,0.222,2,0.111,1,0.222,2]},{"time":0.3333,"x":2,"y":2,"curve":[0.462,2,0.491,1,0.462,2,0.491,1]},{"time":0.5333}]},"bone5":{"scale":[{"curve":[0.169,1,0.364,2,0.169,1,0.364,2]},{"time":0.5333,"x":2,"y":2,"curve":[0.664,2,0.691,1,0.664,2,0.691,1]},{"time":0.7333}]},"bone6":{"scale":[{"curve":[0.226,1,0.507,2,0.226,1,0.507,2]},{"time":0.7333,"x":2,"y":2,"curve":[0.856,2,0.904,1,0.856,2,0.904,1]},{"time":0.9333}]},"bone7":{"scale":[{},{"time":0.9333,"x":2,"y":2,"curve":[1.076,2,1.1,1,1.076,2,1.1,1]},{"time":1.1333}]},"bone8":{"scale":[{"time":1.5667,"x":3,"y":3,"curve":[1.933,3,1.693,1,1.933,3,1.693,1]},{"time":1.9333}]},"bone10":{"translate":[{"x":1950.23},{"time":3.1333,"x":-2507.77}]}}},"Boss appears2":{"slots":{"Ingame_warning_Boss":{"rgba":[{"time":0.9333,"color":"00000000","curve":[0.989,0,1.044,0,0.989,0,1.044,0,0.989,0,1.044,0,0.989,0.33,1.044,1]},{"time":1.1,"color":"000000ff","curve":"stepped"},{"time":1.6667,"color":"000000ff","curve":[1.891,0,1.845,1,1.891,0,1.845,1,1.891,0,1.845,1,1.767,1,1.92,1]},{"time":2,"color":"ffffffff"}],"attachment":[{},{"time":0.9333,"name":"Ingame_warning_Boss_2"}]},"Ingame_warning_Bossname":{"rgba":[{"time":1.5,"color":"ffffff00","curve":[1.644,1,1.789,1,1.644,1,1.789,1,1.644,1,1.789,1,1.933,0,1.649,1]},{"time":1.9333,"color":"ffffffff"}],"attachment":[{},{"time":1.5667,"name":"Ingame_warning_Bossname_2"}]},"Ingame_warning_warning!":{"attachment":[{"time":2.6667},{"time":2.7333,"name":"Ingame_warning_warning!"}]},"Ingame_warning_warning!2":{"attachment":[{"time":2.6667},{"time":2.7333,"name":"Ingame_warning_warning!"}]},"Ingame_warning_warning!3":{"attachment":[{},{"time":1.3333,"name":"Ingame_warning_warning!"}]},"Ingame_warning_warning!4":{"attachment":[{},{"time":1.3333,"name":"Ingame_warning_warning!"}]},"보":{"attachment":[{},{"time":0.3333,"name":"보"}]},"스":{"attachment":[{},{"time":0.5333,"name":"스"}]},"출":{"attachment":[{},{"time":0.7333,"name":"출"}]},"현":{"attachment":[{},{"time":0.9333,"name":"현"}]}},"bones":{"bone":{"scale":[{"x":0},{"time":0.3}]},"bone2":{"translate":[{"x":1950.23},{"time":2.6667,"x":-1845.9},{"time":2.7,"x":2259.71},{"time":2.7333,"x":1972.99},{"time":3.1333,"x":1409.31}]},"bone4":{"scale":[{"curve":[0.111,1,0.222,2,0.111,1,0.222,2]},{"time":0.3333,"x":2,"y":2,"curve":[0.462,2,0.491,1,0.462,2,0.491,1]},{"time":0.5333}]},"bone5":{"scale":[{"curve":[0.169,1,0.364,2,0.169,1,0.364,2]},{"time":0.5333,"x":2,"y":2,"curve":[0.664,2,0.691,1,0.664,2,0.691,1]},{"time":0.7333}]},"bone6":{"scale":[{"curve":[0.226,1,0.507,2,0.226,1,0.507,2]},{"time":0.7333,"x":2,"y":2,"curve":[0.856,2,0.904,1,0.856,2,0.904,1]},{"time":0.9333}]},"bone7":{"scale":[{},{"time":0.9333,"x":2,"y":2,"curve":[1.076,2,1.1,1,1.076,2,1.1,1]},{"time":1.1333}]},"bone8":{"scale":[{"time":1.5667,"x":3,"y":3,"curve":[1.933,3,1.693,1,1.933,3,1.693,1]},{"time":1.9333}]},"bone10":{"translate":[{"x":1950.23},{"time":3.1333,"x":-2507.77}]}}},"Boss appears3":{"slots":{"Ingame_warning_Boss":{"rgba":[{"time":0.9333,"color":"00000000","curve":[0.989,0,1.044,0,0.989,0,1.044,0,0.989,0,1.044,0,0.989,0.33,1.044,1]},{"time":1.1,"color":"000000ff","curve":"stepped"},{"time":1.6667,"color":"000000ff","curve":[1.891,0,1.845,1,1.891,0,1.845,1,1.891,0,1.845,1,1.767,1,1.92,1]},{"time":2,"color":"ffffffff"}],"attachment":[{},{"time":0.9333,"name":"Ingame_warning_Boss_3"}]},"Ingame_warning_Bossname":{"rgba":[{"time":1.5,"color":"ffffff00","curve":[1.644,1,1.789,1,1.644,1,1.789,1,1.644,1,1.789,1,1.933,0,1.649,1]},{"time":1.9333,"color":"ffffffff"}],"attachment":[{},{"time":1.5667,"name":"Ingame_warning_Bossname_3"}]},"Ingame_warning_warning!":{"attachment":[{"time":2.6667},{"time":2.7333,"name":"Ingame_warning_warning!"}]},"Ingame_warning_warning!2":{"attachment":[{"time":2.6667},{"time":2.7333,"name":"Ingame_warning_warning!"}]},"Ingame_warning_warning!3":{"attachment":[{},{"time":1.3333,"name":"Ingame_warning_warning!"}]},"Ingame_warning_warning!4":{"attachment":[{},{"time":1.3333,"name":"Ingame_warning_warning!"}]},"보":{"attachment":[{},{"time":0.3333,"name":"보"}]},"스":{"attachment":[{},{"time":0.5333,"name":"스"}]},"출":{"attachment":[{},{"time":0.7333,"name":"출"}]},"현":{"attachment":[{},{"time":0.9333,"name":"현"}]}},"bones":{"bone":{"scale":[{"x":0},{"time":0.3}]},"bone2":{"translate":[{"x":1950.23},{"time":2.6667,"x":-1845.9},{"time":2.7,"x":2259.71},{"time":2.7333,"x":1972.99},{"time":3.1333,"x":1409.31}]},"bone4":{"scale":[{"curve":[0.111,1,0.222,2,0.111,1,0.222,2]},{"time":0.3333,"x":2,"y":2,"curve":[0.462,2,0.491,1,0.462,2,0.491,1]},{"time":0.5333}]},"bone5":{"scale":[{"curve":[0.169,1,0.364,2,0.169,1,0.364,2]},{"time":0.5333,"x":2,"y":2,"curve":[0.664,2,0.691,1,0.664,2,0.691,1]},{"time":0.7333}]},"bone6":{"scale":[{"curve":[0.226,1,0.507,2,0.226,1,0.507,2]},{"time":0.7333,"x":2,"y":2,"curve":[0.856,2,0.904,1,0.856,2,0.904,1]},{"time":0.9333}]},"bone7":{"scale":[{},{"time":0.9333,"x":2,"y":2,"curve":[1.076,2,1.1,1,1.076,2,1.1,1]},{"time":1.1333}]},"bone8":{"scale":[{"time":1.5667,"x":3,"y":3,"curve":[1.933,3,1.693,1,1.933,3,1.693,1]},{"time":1.9333}]},"bone10":{"translate":[{"x":1950.23},{"time":3.1333,"x":-2507.77}]}}}}}